{"b1bfd0f0e88468dee2920c56f08c3ca1":{"statistic":{"failed":1,"broken":0,"skipped":0,"passed":0,"unknown":0,"total":1},"items":[{"uid":"5d480c2103172421","status":"failed","statusDetails":"AssertionError: 测试失败，失败用例条数：6\nassert False","time":{"start":1709154359993,"stop":1709154371608,"duration":11615}}]},"f330da30b62f17ed1ba2cdc58812afbe":{"statistic":{"failed":0,"broken":0,"skipped":0,"passed":1,"unknown":0,"total":1},"items":[{"uid":"16f85537f7141dc3","status":"passed","time":{"start":1709154371616,"stop":1709154382945,"duration":11329}}]},"7605b9c3cadbccd0d74c5209d08032d7":{"statistic":{"failed":0,"broken":0,"skipped":0,"passed":1,"unknown":0,"total":1},"items":[{"uid":"20a28928b8c644f6","status":"passed","time":{"start":1709154348664,"stop":1709154359990,"duration":11326}}]},"7db1c1f982d8caf5dda8d59e6fdce627":{"statistic":{"failed":0,"broken":0,"skipped":0,"passed":1,"unknown":0,"total":1},"items":[{"uid":"12f32b3197786ce3","status":"passed","time":{"start":1709154817420,"stop":1709154921077,"duration":103657}}]},"4765b0f010c4ee365d68b861f1815adf":{"statistic":{"failed":0,"broken":0,"skipped":0,"passed":1,"unknown":0,"total":1},"items":[{"uid":"16f0bba3f97d0d0e","status":"passed","time":{"start":1709154382947,"stop":1709154817418,"duration":434471}}]},"efbfa347c00e5411482a9cb6fa5166bf":{"statistic":{"failed":1,"broken":0,"skipped":0,"passed":0,"unknown":0,"total":1},"items":[{"uid":"77cf65c01129bba9","status":"failed","statusDetails":"AssertionError: 测试失败，失败用例条数：108\nassert False","time":{"start":1709154326203,"stop":1709154348658,"duration":22455}}]},"1abc4cf2a83690af69b69edbd1bd13fb":{"statistic":{"failed":1,"broken":0,"skipped":0,"passed":0,"unknown":0,"total":1},"items":[{"uid":"bb7da343efd2fc3d","status":"failed","statusDetails":"AssertionError: 测试失败，失败用例条数：1\nassert False","time":{"start":1709154272399,"stop":1709154326162,"duration":53763}}]}}